flowtool_versioning/__init__.py
flowtool_versioning/_version.py
flowtool_versioning/deploy.py
flowtool_versioning/dropins/__init__.py
flowtool_versioning/dropins/cmdclass.py
flowtool_versioning/dropins/version.py
flowtool_versioning-0.7.58.dist-info/DESCRIPTION.rst
flowtool_versioning-0.7.58.dist-info/METADATA
flowtool_versioning-0.7.58.dist-info/RECORD
flowtool_versioning-0.7.58.dist-info/WHEEL
flowtool_versioning-0.7.58.dist-info/entry_points.txt
flowtool_versioning-0.7.58.dist-info/metadata.json
flowtool_versioning-0.7.58.dist-info/top_level.txt
tests/__init__.py
tests/conftest.py
tests/setup_command.py
tests/test_deploy.py
