Metadata-Version: 2.0
Name: flowtool-versioning
Version: 0.7.58
Summary: Semi-automatic versioning for git users.
Home-page: https://github.com/isnok/py-flowlib
Author: Konstantin Martini
Author-email: k@tuxcode.org
License: UNKNOWN
Keywords: git,flow,shell,local,remote,commandline
Platform: Debian/GNU Linux
Classifier: Development Status :: 3 - Alpha
Classifier: Programming Language :: Python
Classifier: Programming Language :: Python :: 2.7
Classifier: Programming Language :: Python :: 3.3
Classifier: Programming Language :: Python :: 3.4
Classifier: Programming Language :: Python :: 3.5
Classifier: Topic :: System :: Software Distribution
Classifier: Topic :: System :: Systems Administration
Classifier: Topic :: Utilities
Classifier: Intended Audience :: Developers
Classifier: Intended Audience :: System Administrators
Classifier: Operating System :: POSIX
Classifier: Operating System :: Unix
Classifier: Environment :: Console
Requires-Dist: flowtool-base (>=0.7.56)
